rcis/__init__.py
rcis/__main__.py
rcis/cli.py
rcis/rcis.py
rcis-1.0.0.dist-info/AUTHORS.rst
rcis-1.0.0.dist-info/LICENSE
rcis-1.0.0.dist-info/METADATA
rcis-1.0.0.dist-info/WHEEL
rcis-1.0.0.dist-info/entry_points.txt
rcis-1.0.0.dist-info/top_level.txt
rcis-1.0.0.dist-info/RECORD
