Metadata-Version: 2.1
Name: rcis
Version: 1.0.0
Summary: Framework for iterative solver via reverse communication
Home-page: https://github.com/enricofacca/rcis
Author: Enrico Facca
Author-email: enrico.facca@gmail.com
License: LGPL-3.0-or-later
Project-URL: Documentation, https://rcis.readthedocs.io/
Project-URL: Changelog, https://rcis.readthedocs.io/en/latest/changelog.html
Project-URL: Issue Tracker, https://github.com/enricofacca/rcis/issues
Platform: UNKNOWN
Classifier: Development Status :: 5 - Production/Stable
Classifier: Intended Audience :: Developers
Classifier: License :: OSI Approved :: GNU Lesser General Public License v3 or later (LGPLv3+)
Classifier: Operating System :: Unix
Classifier: Operating System :: POSIX
Classifier: Operating System :: Microsoft :: Windows
Classifier: Programming Language :: Python
Classifier: Programming Language :: Python :: 3
Classifier: Programming Language :: Python :: 3 :: Only
Classifier: Programming Language :: Python :: 3.6
Classifier: Programming Language :: Python :: 3.7
Classifier: Programming Language :: Python :: 3.8
Classifier: Programming Language :: Python :: 3.9
Classifier: Programming Language :: Python :: 3.10
Classifier: Programming Language :: Python :: Implementation :: CPython
Classifier: Programming Language :: Python :: Implementation :: PyPy
Classifier: Topic :: Utilities
Requires-Python: >=3.6
Requires-Dist: numpy (>=1.19.0)
